PyFaudit/__init__.py
PyFaudit/scanner.py
PyFaudit-0.1.0.dist-info/METADATA
PyFaudit-0.1.0.dist-info/WHEEL
PyFaudit-0.1.0.dist-info/entry_points.txt
PyFaudit-0.1.0.dist-info/top_level.txt
PyFaudit-0.1.0.dist-info/RECORD
