Metadata-Version: 2.1
Name: PyFaudit
Version: 0.1.0
Summary: A python package to scan Python files, check encoding issues and provide an audit summary
Author-email: "Mr. Mendez" <info@mrmendez.dev>
Project-URL: Source, https://github.com/justmrmendez/PyFaudit
Project-URL: Home, https://github.com/justmrmendez/PyFaudit
Project-URL: Documentation, https://github.com/justmrmendez/PyFaudit
Classifier: Programming Language :: Python :: 3
Classifier: License :: OSI Approved :: MIT License
